superapi/__init__.py
superapi/version.py
superapi-1.0.2.dist-info/LICENSE
superapi-1.0.2.dist-info/METADATA
superapi-1.0.2.dist-info/WHEEL
superapi-1.0.2.dist-info/top_level.txt
superapi-1.0.2.dist-info/RECORD
