Metadata-Version: 2.1
Name: superapi
Version: 1.0.2
Summary: a lightweight API framework
Home-page: https://github.com/fred913/ftapi
Author: Sheng Fan
Author-email: 1175882937@qq.com
License: GPL-2.0
Platform: any
Requires: pip
Requires: flask
Requires-Python: >=2.7
